ProcessMVNX/ProcessMVNX.py
ProcessMVNX/__init__.py
ProcessMVNX/bvh_import.py
ProcessMVNX-0.2.4.dist-info/METADATA
ProcessMVNX-0.2.4.dist-info/RECORD
ProcessMVNX-0.2.4.dist-info/WHEEL
ProcessMVNX-0.2.4.dist-info/top_level.txt
