Metadata-Version: 2.1
Name: ProcessMVNX
Version: 0.2.4
Summary: Tool for reading and processing MVNX-Files from the xsens-Awinda Motion Capturing System.
Home-page: https://gitlab.com/Benjamin_Knopp/ProcessMVNX
Author: Benjamin Knopp
Author-email: knoppbe@staff.uni-marburg.de
License: MIT
Platform: UNKNOWN
Classifier: Development Status :: 2 - Pre-Alpha
Classifier: Intended Audience :: Science/Research
Classifier: License :: OSI Approved :: MIT License
Classifier: Natural Language :: English
Classifier: Operating System :: POSIX :: Linux
Classifier: Programming Language :: Python :: 3
Classifier: Topic :: Utilities
Requires-Dist: pytest
Requires-Dist: numpy
Requires-Dist: pandas
Requires-Dist: transforms3d
Requires-Dist: matplotlib
